earth_api/__init__.py
earth_api/api_wrapper/__init__.py
earth_api/api_wrapper/api_wrapper.py
earth_api/api_wrapper/earth_api.py
earth_api/api_wrapper/http_api_wrapper.py
earth_api/api_wrapper/swagger_api_wrapper.py
earth_api/swagger_client/__init__.py
earth_api/swagger_client/api_client.py
earth_api/swagger_client/configuration.py
earth_api/swagger_client/rest.py
earth_api/swagger_client/api/__init__.py
earth_api/swagger_client/api/camera_api.py
earth_api/swagger_client/api/content_api.py
earth_api/swagger_client/api/drawings_api.py
earth_api/swagger_client/api/flight_api.py
earth_api/swagger_client/api/graphics_api.py
earth_api/swagger_client/api/layer_api.py
earth_api/swagger_client/api/layers_api.py
earth_api/swagger_client/api/snapshot_api.py
earth_api/swagger_client/api/workspace_api.py
earth_api/swagger_client/models/__init__.py
earth_api/swagger_client/models/age_camera.py
earth_api/swagger_client/models/age_datasource.py
earth_api/swagger_client/models/age_drawing.py
earth_api/swagger_client/models/age_flight.py
earth_api/swagger_client/models/age_map_point.py
earth_api/swagger_client/models/age_spatial_reference.py
earth_api/swagger_client/models/age_workspace.py
earth_api/swagger_client/models/j_token.py
earth_api-0.0.4.dist-info/METADATA
earth_api-0.0.4.dist-info/WHEEL
earth_api-0.0.4.dist-info/top_level.txt
earth_api-0.0.4.dist-info/RECORD
