Metadata-Version: 2.1
Name: earth-api
Version: 0.0.4
Summary: ArcGIS Earth Automation API
Home-page: UNKNOWN
Author-email: 
License: UNKNOWN
Keywords: Swagger,ArcGIS Earth Automation API
Platform: UNKNOWN
Requires-Dist: urllib3 (>=1.15)
Requires-Dist: six (>=1.10)
Requires-Dist: certifi
Requires-Dist: python-dateutil
Requires-Dist: requests
Requires-Dist: od
